beyond/__init__.py
beyond/config.py
beyond/constants.py
beyond/errors.py
beyond/dates/__init__.py
beyond/dates/date.py
beyond/dates/eop.py
beyond/env/__init__.py
beyond/env/jpl.py
beyond/env/solarsystem.py
beyond/frames/__init__.py
beyond/frames/center.py
beyond/frames/frames.py
beyond/frames/iau1980.py
beyond/frames/iau2010.py
beyond/frames/lagrange.py
beyond/frames/local.py
beyond/frames/orient.py
beyond/frames/stations.py
beyond/frames/data/tab5.1.txt
beyond/frames/data/tab5.2a.txt
beyond/frames/data/tab5.2b.txt
beyond/frames/data/tab5.2d.txt
beyond/io/__init__.py
beyond/io/horizon.py
beyond/io/tle.py
beyond/io/ccsds/__init__.py
beyond/io/ccsds/ccsds.py
beyond/io/ccsds/commons.py
beyond/io/ccsds/cov.py
beyond/io/ccsds/oem.py
beyond/io/ccsds/omm.py
beyond/io/ccsds/opm.py
beyond/io/ccsds/tdm.py
beyond/orbits/__init__.py
beyond/orbits/cov.py
beyond/orbits/ephem.py
beyond/orbits/forms.py
beyond/orbits/man.py
beyond/orbits/orbit.py
beyond/orbits/statevector.py
beyond/propagators/__init__.py
beyond/propagators/_soi.py
beyond/propagators/base.py
beyond/propagators/listeners.py
beyond/propagators/analytical/__init__.py
beyond/propagators/analytical/eh.py
beyond/propagators/analytical/j2.py
beyond/propagators/analytical/kepler.py
beyond/propagators/analytical/none.py
beyond/propagators/analytical/sgp4.py
beyond/propagators/analytical/sgp4beta.py
beyond/propagators/analytical/soi.py
beyond/propagators/numerical/__init__.py
beyond/propagators/numerical/keplernum.py
beyond/propagators/numerical/soi.py
beyond/propagators/rpo/__init__.py
beyond/propagators/rpo/cw.py
beyond/propagators/rpo/ya.py
beyond/utils/__init__.py
beyond/utils/beta.py
beyond/utils/constellation.py
beyond/utils/interp.py
beyond/utils/interplanetary.py
beyond/utils/lambert.py
beyond/utils/leo.py
beyond/utils/ltan.py
beyond/utils/matrix.py
beyond/utils/measures.py
beyond/utils/memoize.py
beyond/utils/node.py
beyond/utils/rpohelper.py
beyond/utils/units.py
beyond-0.8.1.dist-info/METADATA
beyond-0.8.1.dist-info/WHEEL
beyond-0.8.1.dist-info/licenses/LICENSE.md
beyond-0.8.1.dist-info/RECORD
