Metadata-Version: 2.4
Name: beyond
Version: 0.8.1
Summary: Flight Dynamic Library
Project-URL: Homepage, https://github.com/galactics/beyond
Project-URL: Documentation, https://beyond.readthedocs.io
Project-URL: Repository, https://github.com/galactics/beyond
Project-URL: Issues, https://github.com/galactics/beyond/issues
Project-URL: Changelog, https://github.com/galactics/beyond/blob/master/CHANGELOG.md
Author-email: Jules David <jules@onada.fr>
License-File: LICENSE.md
Keywords: flight dynamic,satellite,space
Classifier: Development Status :: 2 - Pre-Alpha
Classifier: Intended Audience :: Science/Research
Classifier: License :: OSI Approved :: MIT License
Classifier: Operating System :: OS Independent
Classifier: Programming Language :: Python :: 3
Classifier: Programming Language :: Python :: 3.7
Classifier: Programming Language :: Python :: 3.8
Classifier: Programming Language :: Python :: 3.9
Classifier: Programming Language :: Python :: 3.10
Classifier: Programming Language :: Python :: 3.11
Classifier: Programming Language :: Python :: 3.12
Classifier: Programming Language :: Python :: 3.13
Classifier: Topic :: Scientific/Engineering :: Astronomy
Classifier: Topic :: Scientific/Engineering :: Physics
Requires-Python: >=3.6
Requires-Dist: importlib-metadata>=3.6; python_version < '3.10'
Requires-Dist: jplephem
Requires-Dist: lxml
Requires-Dist: numpy
Requires-Dist: sgp4
Provides-Extra: dev
Requires-Dist: sphinx; extra == 'dev'
Requires-Dist: sphinx-rtd-theme; extra == 'dev'
Requires-Dist: tox; extra == 'dev'
Provides-Extra: tests
Requires-Dist: pytest; extra == 'tests'
Requires-Dist: pytest-cov; extra == 'tests'
Requires-Dist: xmlschema>=1.4.1; extra == 'tests'
